CHANGES.txt
LICENSE.txt
MANIFEST.in
README.rst
setup.py
FilterZippedDBF.egg-info/PKG-INFO
FilterZippedDBF.egg-info/SOURCES.txt
FilterZippedDBF.egg-info/dependency_links.txt
FilterZippedDBF.egg-info/top_level.txt
filterzippeddbf/__init__.py
filterzippeddbf/dbasefilter.py
filterzippeddbf/filter.py
filterzippeddbf/help.html
filterzippeddbf/help.rst
filterzippeddbf/urlzippedfile.py