Metadata-Version: 1.1
Name: FilterZippedDBF
Version: 0.2.0
Summary: Filter zipped DBF files to remove data from unwanted fields
Home-page: http://www.solentware.co.uk
Author: Roger Marsh
Author-email: roger.marsh@solentware.co.uk
License: BSD
Keywords: DBF CSV
Platform: UNKNOWN
Classifier: Development Status :: 3 - Alpha
Classifier: Intended Audience :: End Users/Desktop
Classifier: License :: OSI Approved :: BSD License
Classifier: Programming Language :: Python :: 3.3
Classifier: Programming Language :: Python :: 3.4
Classifier: Programming Language :: Python :: 3.5
Classifier: Programming Language :: Python :: 3.6
